plugin_adk/__init__.py
plugin_adk/main.py
plugin_adk-0.1.0.dist-info/METADATA
plugin_adk-0.1.0.dist-info/WHEEL
plugin_adk-0.1.0.dist-info/entry_points.txt
plugin_adk-0.1.0.dist-info/top_level.txt
plugin_adk-0.1.0.dist-info/RECORD
