Metadata-Version: 2.4
Name: plugin-adk
Version: 0.1.0
Summary: A simple Hello World package for plugin-adk
Author-email: OpenMind User <user@example.com>
Classifier: Programming Language :: Python :: 3
Classifier: License :: OSI Approved :: MIT License
Classifier: Operating System :: OS Independent
Requires-Python: >=3.7
